{"name": "Combee", "id": "415", "display_id": "415", "form_name": "", "species_id": "415", "abilities": [{"id": "118", "name": "Honey Gather"}], "hidden_ability": {"id": "55", "name": "Hustle"}, "moves": {"16": {"id": "16", "name": "Gust", "type": "Flying", "priority": "0", "damage_class": "special"}, "230": {"id": "230", "name": "Sweet Scent", "type": "Normal", "priority": "0", "damage_class": "status"}, "129": {"id": "129", "name": "Swift", "type": "Normal", "priority": "0", "damage_class": "special"}, "173": {"id": "173", "name": "Snore", "type": "Normal", "priority": "0", "damage_class": "special"}, "189": {"id": "189", "name": "Mud-Slap", "type": "Ground", "priority": "0", "damage_class": "special"}, "283": {"id": "283", "name": "Endeavor", "type": "Normal", "priority": "0", "damage_class": "physical"}, "314": {"id": "314", "name": "Air Cutter", "type": "Flying", "priority": "0", "damage_class": "special"}, "450": {"id": "450", "name": "Bug Bite", "type": "Bug", "priority": "0", "damage_class": "physical"}, "466": {"id": "466", "name": "Ominous Wind", "type": "Ghost", "priority": "0", "damage_class": "special"}, "81": {"id": "81", "name": "String Shot", "type": "Bug", "priority": "0", "damage_class": "status"}, "366": {"id": "366", "name": "Tailwind", "type": "Flying", "priority": "0", "damage_class": "status"}, "405": {"id": "405", "name": "Bug Buzz", "type": "Bug", "priority": "0", "damage_class": "special"}}, "types": {"7": {"id": "7", "name": "Bug"}, "3": {"id": "3", "name": "Flying"}}, "types_nice": {"Normal": {"multiplier": 1.0, "name": "Normal", "id": 1}, "Fighting": {"multiplier": 0.25, "name": "Fighting", "id": 2}, "Flying": {"multiplier": 2.0, "name": "Flying", "id": 3}, "Poison": {"multiplier": 1.0, "name": "Poison", "id": 4}, "Ground": {"multiplier": 0.0, "name": "Ground", "id": 5}, "Rock": {"multiplier": 4.0, "name": "Rock", "id": 6}, "Bug": {"multiplier": 0.5, "name": "Bug", "id": 7}, "Ghost": {"multiplier": 1.0, "name": "Ghost", "id": 8}, "Steel": {"multiplier": 1.0, "name": "Steel", "id": 9}, "Fire": {"multiplier": 2.0, "name": "Fire", "id": 10}, "Water": {"multiplier": 1.0, "name": "Water", "id": 11}, "Grass": {"multiplier": 0.25, "name": "Grass", "id": 12}, "Electric": {"multiplier": 2.0, "name": "Electric", "id": 13}, "Psychic": {"multiplier": 1.0, "name": "Psychic", "id": 14}, "Ice": {"multiplier": 2.0, "name": "Ice", "id": 15}, "Dragon": {"multiplier": 1.0, "name": "Dragon", "id": 16}, "Dark": {"multiplier": 1.0, "name": "Dark", "id": 17}, "Fairy": {"multiplier": 1.0, "name": "Fairy", "id": 18}}, "ev_yeild": ["0", "0", "0", "0", "0", "1"], "base_stats": ["30", "30", "42", "30", "42", "70"], "generation_debut": "4", "evolves_from": "", "gender_rate": ""}