{"name": "Lampent", "id": "608", "display_id": "608", "form_name": "", "species_id": "608", "abilities": [{"id": "18", "name": "Flash Fire"}, {"id": "49", "name": ""}], "hidden_ability": {"id": "151", "name": "Infiltrator"}, "moves": {"52": {"id": "52", "name": "Ember", "type": "Fire", "priority": "0", "damage_class": "special"}, "53": {"id": "53", "name": "Flamethrower", "type": "Fire", "priority": "0", "damage_class": "special"}, "76": {"id": "76", "name": "Solar Beam", "type": "Grass", "priority": "0", "damage_class": "special"}, "83": {"id": "83", "name": "Fire Spin", "type": "Fire", "priority": "0", "damage_class": "special"}, "92": {"id": "92", "name": "Toxic", "type": "Poison", "priority": "0", "damage_class": "status"}, "94": {"id": "94", "name": "Psychic", "type": "Psychic", "priority": "0", "damage_class": "special"}, "101": {"id": "101", "name": "Night Shade", "type": "Ghost", "priority": "0", "damage_class": "special"}, "104": {"id": "104", "name": "Double Team", "type": "Normal", "priority": "0", "damage_class": "status"}, "107": {"id": "107", "name": "Minimize", "type": "Normal", "priority": "0", "damage_class": "status"}, "109": {"id": "109", "name": "Confuse Ray", "type": "Ghost", "priority": "0", "damage_class": "status"}, "123": {"id": "123", "name": "Smog", "type": "Poison", "priority": "0", "damage_class": "special"}, "126": {"id": "126", "name": "Fire Blast", "type": "Fire", "priority": "0", "damage_class": "special"}, "138": {"id": "138", "name": "Dream Eater", "type": "Psychic", "priority": "0", "damage_class": "special"}, "148": {"id": "148", "name": "Flash", "type": "Normal", "priority": "0", "damage_class": "status"}, "156": {"id": "156", "name": "Rest", "type": "Psychic", "priority": "0", "damage_class": "status"}, "164": {"id": "164", "name": "Substitute", "type": "Normal", "priority": "0", "damage_class": "status"}, "168": {"id": "168", "name": "Thief", "type": "Dark", "priority": "0", "damage_class": "physical"}, "174": {"id": "174", "name": "Curse", "type": "Ghost", "priority": "0", "damage_class": "status"}, "182": {"id": "182", "name": "Protect", "type": "Normal", "priority": "4", "damage_class": "status"}, "207": {"id": "207", "name": "Swagger", "type": "Normal", "priority": "0", "damage_class": "status"}, "213": {"id": "213", "name": "Attract", "type": "Normal", "priority": "0", "damage_class": "status"}, "216": {"id": "216", "name": "Return", "type": "Normal", "priority": "0", "damage_class": "physical"}, "218": {"id": "218", "name": "Frustration", "type": "Normal", "priority": "0", "damage_class": "physical"}, "219": {"id": "219", "name": "Safeguard", "type": "Normal", "priority": "0", "damage_class": "status"}, "220": {"id": "220", "name": "Pain Split", "type": "Normal", "priority": "0", "damage_class": "status"}, "237": {"id": "237", "name": "Hidden Power", "type": "Normal", "priority": "0", "damage_class": "special"}, "241": {"id": "241", "name": "Sunny Day", "type": "Fire", "priority": "0", "damage_class": "status"}, "244": {"id": "244", "name": "Psych Up", "type": "Normal", "priority": "0", "damage_class": "status"}, "247": {"id": "247", "name": "Shadow Ball", "type": "Ghost", "priority": "0", "damage_class": "special"}, "261": {"id": "261", "name": "Will-O-Wisp", "type": "Fire", "priority": "0", "damage_class": "status"}, "262": {"id": "262", "name": "Memento", "type": "Dark", "priority": "0", "damage_class": "status"}, "263": {"id": "263", "name": "Facade", "type": "Normal", "priority": "0", "damage_class": "physical"}, "269": {"id": "269", "name": "Taunt", "type": "Dark", "priority": "0", "damage_class": "status"}, "286": {"id": "286", "name": "Imprison", "type": "Psychic", "priority": "0", "damage_class": "status"}, "310": {"id": "310", "name": "Astonish", "type": "Ghost", "priority": "0", "damage_class": "physical"}, "315": {"id": "315", "name": "Overheat", "type": "Fire", "priority": "0", "damage_class": "special"}, "347": {"id": "347", "name": "Calm Mind", "type": "Psychic", "priority": "0", "damage_class": "status"}, "371": {"id": "371", "name": "Payback", "type": "Dark", "priority": "0", "damage_class": "physical"}, "373": {"id": "373", "name": "Embargo", "type": "Dark", "priority": "0", "damage_class": "status"}, "412": {"id": "412", "name": "Energy Ball", "type": "Grass", "priority": "0", "damage_class": "special"}, "433": {"id": "433", "name": "Trick Room", "type": "Psychic", "priority": "-7", "damage_class": "status"}, "477": {"id": "477", "name": "Telekinesis", "type": "Psychic", "priority": "0", "damage_class": "status"}, "481": {"id": "481", "name": "Flame Burst", "type": "Fire", "priority": "0", "damage_class": "special"}, "488": {"id": "488", "name": "Flame Charge", "type": "Fire", "priority": "0", "damage_class": "physical"}, "496": {"id": "496", "name": "Round", "type": "Normal", "priority": "0", "damage_class": "special"}, "506": {"id": "506", "name": "Hex", "type": "Ghost", "priority": "0", "damage_class": "special"}, "510": {"id": "510", "name": "Incinerate", "type": "Fire", "priority": "0", "damage_class": "special"}, "517": {"id": "517", "name": "Inferno", "type": "Fire", "priority": "0", "damage_class": "special"}, "173": {"id": "173", "name": "Snore", "type": "Normal", "priority": "0", "damage_class": "special"}, "180": {"id": "180", "name": "Spite", "type": "Ghost", "priority": "0", "damage_class": "status"}, "214": {"id": "214", "name": "Sleep Talk", "type": "Normal", "priority": "0", "damage_class": "status"}, "257": {"id": "257", "name": "Heat Wave", "type": "Fire", "priority": "0", "damage_class": "special"}, "271": {"id": "271", "name": "Trick", "type": "Psychic", "priority": "0", "damage_class": "status"}, "399": {"id": "399", "name": "Dark Pulse", "type": "Dark", "priority": "0", "damage_class": "special"}, "590": {"id": "590", "name": "Confide", "type": "Normal", "priority": "0", "damage_class": "status"}, "290": {"id": "290", "name": "Secret Power", "type": "Normal", "priority": "0", "damage_class": "physical"}, "351": {"id": "351", "name": "Shock Wave", "type": "Electric", "priority": "0", "damage_class": "special"}, "51": {"id": "51", "name": "Acid", "type": "Poison", "priority": "0", "damage_class": "special"}, "114": {"id": "114", "name": "Haze", "type": "Ice", "priority": "0", "damage_class": "status"}, "151": {"id": "151", "name": "Acid Armor", "type": "Poison", "priority": "0", "damage_class": "status"}, "203": {"id": "203", "name": "Endure", "type": "Normal", "priority": "4", "damage_class": "status"}, "445": {"id": "445", "name": "Captivate", "type": "Normal", "priority": "0", "damage_class": "status"}, "499": {"id": "499", "name": "Clear Smog", "type": "Poison", "priority": "0", "damage_class": "special"}, "471": {"id": "471", "name": "Power Split", "type": "Psychic", "priority": "0", "damage_class": "status"}}, "types": {"8": {"id": "8", "name": "Ghost"}, "10": {"id": "10", "name": "Fire"}}, "types_nice": {"Normal": {"multiplier": 0.0, "name": "Normal", "id": 1}, "Fighting": {"multiplier": 0.0, "name": "Fighting", "id": 2}, "Flying": {"multiplier": 1.0, "name": "Flying", "id": 3}, "Poison": {"multiplier": 0.5, "name": "Poison", "id": 4}, "Ground": {"multiplier": 2.0, "name": "Ground", "id": 5}, "Rock": {"multiplier": 2.0, "name": "Rock", "id": 6}, "Bug": {"multiplier": 0.25, "name": "Bug", "id": 7}, "Ghost": {"multiplier": 2.0, "name": "Ghost", "id": 8}, "Steel": {"multiplier": 0.5, "name": "Steel", "id": 9}, "Fire": {"multiplier": 0.5, "name": "Fire", "id": 10}, "Water": {"multiplier": 2.0, "name": "Water", "id": 11}, "Grass": {"multiplier": 0.5, "name": "Grass", "id": 12}, "Electric": {"multiplier": 1.0, "name": "Electric", "id": 13}, "Psychic": {"multiplier": 1.0, "name": "Psychic", "id": 14}, "Ice": {"multiplier": 0.5, "name": "Ice", "id": 15}, "Dragon": {"multiplier": 1.0, "name": "Dragon", "id": 16}, "Dark": {"multiplier": 2.0, "name": "Dark", "id": 17}, "Fairy": {"multiplier": 0.5, "name": "Fairy", "id": 18}}, "ev_yeild": ["0", "0", "0", "2", "0", "0"], "base_stats": ["60", "40", "60", "95", "60", "55"], "generation_debut": "5", "evolves_from": "607", "gender_rate": ""}