{"name": "Liquid Ooze", "id": "64", "generation-introduced": "3", "short-desc": "Damages opponents using leeching moves for as much as they would heal. ", "long-desc": "Whenever a Pokemon would heal after hitting this Pokemon with a leeching move like , it instead loses as many HP as it would usually gain.   is unaffected. ", "pokemonWithAbility": [{"name": "Tentacool", "id": "72", "types": {"11": {"id": "11", "name": "Water"}, "4": {"id": "4", "name": "Poison"}}, "ha": false}, {"name": "Tentacruel", "id": "73", "types": {"11": {"id": "11", "name": "Water"}, "4": {"id": "4", "name": "Poison"}}, "ha": false}, {"name": "Gulpin", "id": "316", "types": {"4": {"id": "4", "name": "Poison"}}, "ha": false}, {"name": "Swalot", "id": "317", "types": {"4": {"id": "4", "name": "Poison"}}, "ha": false}]}